{"is_source_file": true, "format": "CSS", "description": "This CSS file contains style definitions for a theme management system, with variables for light and dark themes, along with styles for various components such as the App, headers, links, and theme toggle button.", "external_files": [], "external_methods": [], "published": [], "classes": [{"name": "App", "description": "Main application styling including alignment, background color, and text color."}, {"name": "App-header", "description": "Styling for the header component including background color and layout."}, {"name": "App-logo", "description": "Styling for the application logo, including size and animations."}, {"name": "App-link", "description": "Styling for links within the application."}, {"name": "theme-toggle", "description": "Styling for the theme toggle button, including positioning and hover effects."}], "methods": [{"name": "App-logo-spin", "description": "Animation keyframes for spinning the application logo."}], "calls": [], "search-terms": ["theme management", "dark mode", "light mode", "responsive design", "App styles"], "state": 2, "file_id": 5, "knowledge_revision": 20, "git_revision": "5eb982ff9b03e18a77e8434a53c285a43caa3265", "hash": "22f9e17cc1848b56dbb244518ac2707e", "format-version": 4, "code-base-name": "tic_tac_toe_frontend", "filename": "tic_tac_toe_frontend/src/App.css", "revision_history": [{"20": "5eb982ff9b03e18a77e8434a53c285a43caa3265"}]}